{
  "total_comparisons": 465,
  "num_samples": 30,
  "num_genuine_pairs": 135,
  "num_impostor_pairs": 300,
  "num_same_file": 30,
  "output_file": "/media/DRAGONSTONE/MEGAsync/Forense/Papiloscopia/Compara_Metodos_Automaticos/Plataformas/Experimento/exp0_baseline/results/pairwise_comparisons_debug_minimal.csv",
  "total_time_seconds": 0.09687089920043945,
  "memory_peak_mb": 1705.21484375,
  "memory_avg_mb": 1705.21484375,
  "cpu_avg_percent": 0.0,
  "gpu_memory_peak_mb": 810.63818359375,
  "num_measurements": 1,
  "genuine_score_mean": 0.9187535418404473,
  "genuine_score_std": 0.09819800040875441,
  "impostor_score_mean": 0.9059874780972799,
  "impostor_score_std": 0.0973853229452079
}